stimupy/__init__.py
stimupy/logos.py
stimupy/_docs/__init__.py
stimupy/_docs/compare_functions_pngs.py
stimupy/_docs/display_stimulus.py
stimupy/_docs/generate_stimulus_images.py
stimupy/_docs/params/__init__.py
stimupy/_docs/params/components/__init__.py
stimupy/_docs/params/components/angulars.py
stimupy/_docs/params/components/edges.py
stimupy/_docs/params/components/frames.py
stimupy/_docs/params/components/gaussians.py
stimupy/_docs/params/components/lines.py
stimupy/_docs/params/components/radials.py
stimupy/_docs/params/components/shapes.py
stimupy/_docs/params/components/texts.py
stimupy/_docs/params/components/waves.py
stimupy/_docs/params/noises/__init__.py
stimupy/_docs/params/noises/binaries.py
stimupy/_docs/params/noises/narrowbands.py
stimupy/_docs/params/noises/naturals.py
stimupy/_docs/params/noises/whites.py
stimupy/_docs/params/stimuli/__init__.py
stimupy/_docs/params/stimuli/benarys.py
stimupy/_docs/params/stimuli/bullseyes.py
stimupy/_docs/params/stimuli/checkerboards.py
stimupy/_docs/params/stimuli/cornsweets.py
stimupy/_docs/params/stimuli/cubes.py
stimupy/_docs/params/stimuli/delboeufs.py
stimupy/_docs/params/stimuli/dungeons.py
stimupy/_docs/params/stimuli/edges.py
stimupy/_docs/params/stimuli/gabors.py
stimupy/_docs/params/stimuli/gratings.py
stimupy/_docs/params/stimuli/hermanns.py
stimupy/_docs/params/stimuli/mondrians.py
stimupy/_docs/params/stimuli/mueller_lyers.py
stimupy/_docs/params/stimuli/pinwheels.py
stimupy/_docs/params/stimuli/plaids.py
stimupy/_docs/params/stimuli/ponzos.py
stimupy/_docs/params/stimuli/rings.py
stimupy/_docs/params/stimuli/sbcs.py
stimupy/_docs/params/stimuli/todorovics.py
stimupy/_docs/params/stimuli/waves.py
stimupy/_docs/params/stimuli/wedding_cakes.py
stimupy/_docs/params/stimuli/whites.py
stimupy/components/__init__.py
stimupy/components/angulars.py
stimupy/components/edges.py
stimupy/components/frames.py
stimupy/components/gaussians.py
stimupy/components/lines.py
stimupy/components/radials.py
stimupy-1.2.0.dist-info/licenses/LICENSE
stimupy-1.2.0.dist-info/METADATA
stimupy-1.2.0.dist-info/WHEEL
stimupy-1.2.0.dist-info/top_level.txt
stimupy-1.2.0.dist-info/RECORD
