Metadata-Version: 2.4
Name: stimupy
Version: 1.2.0
Summary: Stimuli for vision science, as image arrays
Author: Matko Matic, Guillermo Aguilar, Marianne Maertens
Author-email: Lynn Schmittwilken <l.schmittwilken@tu-berlin.de>, Joris Vincent <j.vincent@tu-berlin.de>
Maintainer-email: Lynn Schmittwilken <l.schmittwilken@tu-berlin.de>, Joris Vincent <j.vincent@tu-berlin.de>
License: GNU GENERAL PUBLIC LICENSE
Project-URL: repository, https://github.com/computational-psychology/stimupy.git
Keywords: stimulus,visual perception,psychophysics
Classifier: Development Status :: 4 - Beta
Classifier: Programming Language :: Python
Classifier: Intended Audience :: Science/Research
Classifier: Topic :: Scientific/Engineering
Requires-Python: >=3.9
License-File: LICENSE
Requires-Dist: numpy<2.3
Requires-Dist: scipy
Requires-Dist: matplotlib
Requires-Dist: pandas
Requires-Dist: Pillow
Dynamic: license-file
